async_vk_bot/__init__.py
async_vk_bot/bot.py
async_vk_bot/dispatcher.py
async_vk_bot/factories.py
async_vk_bot/poller.py
async_vk_bot/utils.py
async_vk_bot-0.9.5.dist-info/METADATA
async_vk_bot-0.9.5.dist-info/WHEEL
async_vk_bot-0.9.5.dist-info/top_level.txt
async_vk_bot-0.9.5.dist-info/RECORD
