Metadata-Version: 2.1
Name: async-vk-bot
Version: 0.9.5
Summary: Async VK bot builder
Home-page: https://github.com/Suenweek/async-vk-bot
Author: Roman Novatorov
Author-email: roman.novatorov@gmail.com
License: UNKNOWN
Platform: UNKNOWN
Requires-Dist: async-vk-api (==0.6.1)
Requires-Dist: async-generator
